AUTHORS
ChangeLog
MANIFEST.in
README.rst
requirements.txt
setup.cfg
setup.py
leonardo_geo/__init__.py
leonardo_geo/models.py
leonardo_geo.egg-info/PKG-INFO
leonardo_geo.egg-info/SOURCES.txt
leonardo_geo.egg-info/dependency_links.txt
leonardo_geo.egg-info/not-zip-safe
leonardo_geo.egg-info/pbr.json
leonardo_geo.egg-info/top_level.txt
leonardo_geo/locale/cs/LC_MESSAGES/django.po
leonardo_geo/locale/de/LC_MESSAGES/django.po
leonardo_geo/locale/sk/LC_MESSAGES/django.po
leonardo_geo/templates/widget/maplocation/default.html
leonardo_geo/templates/widget/maplocation/styled.html
leonardo_geo/widget/__init__.py
leonardo_geo/widget/maplocation/__init__.py
leonardo_geo/widget/maplocation/models.py